{
  "english": "unbend",
  "phat_am": "[,ʌn'bend]",
  "list_type": [
    {
      "type": "ngoại động từ unbent",
      "list_m": [
        {
          "m_full_vn": "kéo thẳng, vuốt thẳng, uốn thẳng"
        },
        {
          "m_full_vn": "tháo ra, làm lơi ra, nới ra"
        },
        {
          "m_full_vn": "duỗi thẳng ra"
        },
        {
          "m_full_vn": "giải (trí), làm cho (trí óc) đỡ căng thẳng"
        },
        {
          "m_full_vn": "(hàng hải) tháo (dây buộc)"
        }
      ]
    },
    {
      "type": "nội động từ",
      "list_m": [
        {
          "m_full_vn": "thẳng ra, duỗi ra; lơi ra"
        },
        {
          "m_full_vn": "thấy đỡ căng thẳng (trí óc)"
        },
        {
          "m_full_vn": "dịu bớt (nét mặt)"
        },
        {
          "m_full_vn": "xuề xoà, trở nên thoải mái, trở nên bớt căng thẳng, không câu nệ (trong ứng xử)"
        }
      ]
    }
  ]
}